LICENSE
MANIFEST.in
README.md
requirements.txt
setup.py
libra_python.egg-info/PKG-INFO
libra_python.egg-info/SOURCES.txt
libra_python.egg-info/dependency_links.txt
libra_python.egg-info/requires.txt
libra_python.egg-info/top_level.txt
pylibra/__init__.py
pylibra/client.py
pylibra/proto/__init__.py
pylibra/proto/access_path_pb2.py
pylibra/proto/access_path_pb2_grpc.py
pylibra/proto/account_state_blob_pb2.py
pylibra/proto/account_state_blob_pb2_grpc.py
pylibra/proto/admission_control_pb2.py
pylibra/proto/admission_control_pb2_grpc.py
pylibra/proto/events_pb2.py
pylibra/proto/events_pb2_grpc.py
pylibra/proto/get_with_proof_pb2.py
pylibra/proto/get_with_proof_pb2_grpc.py
pylibra/proto/ledger_info_pb2.py
pylibra/proto/ledger_info_pb2_grpc.py
pylibra/proto/mempool_status_pb2.py
pylibra/proto/mempool_status_pb2_grpc.py
pylibra/proto/proof_pb2.py
pylibra/proto/proof_pb2_grpc.py
pylibra/proto/transaction_info_pb2.py
pylibra/proto/transaction_info_pb2_grpc.py
pylibra/proto/transaction_pb2.py
pylibra/proto/transaction_pb2_grpc.py
pylibra/proto/validator_change_pb2.py
pylibra/proto/validator_change_pb2_grpc.py
pylibra/proto/vm_errors_pb2.py
pylibra/proto/vm_errors_pb2_grpc.py
pylibra/transaction/__init__.py
pylibra/transaction/base.py
pylibra/transaction/transfer.py
pylibra/wallet/__init__.py
pylibra/wallet/account.py
pylibra/wallet/account_state.py