Metadata-Version: 1.1
Name: libra-python
Version: 0.1.5
Summary: A Python client for Libra network
Home-page: https://github.com/bandprotocol/pylibra
Author: Band Protocol
Author-email: opensource@bandprotocol.com
License: MIT
Keywords: libra,client,cryptocurrency,blockchain
Platform: UNKNOWN
Classifier: Intended Audience :: Developers
Classifier: License :: OSI Approved :: MIT License
Classifier: Operating System :: POSIX :: Linux
Classifier: Operating System :: Microsoft :: Windows
Classifier: Operating System :: MacOS :: MacOS X
